quple/__init__.py
quple/_version.py
quple/circuits/__init__.py
quple/circuits/common_circuits.py
quple/circuits/parameterised_circuit.py
quple/circuits/quantum_circuit.py
quple/circuits/quantum_circuit_test.py
quple/circuits/qubit_register.py
quple/circuits/templates/__init__.py
quple/circuits/templates/parameterised_block.py
quple/circuits/templates/pauli_block.py
quple/circuits/templates/riswap_block.py
quple/circuits/templates/template_circuit_block.py
quple/circuits/variational_circuits/__init__.py
quple/circuits/variational_circuits/efficient_su2.py
quple/circuits/variational_circuits/excitation_preserving.py
quple/circuits/variational_circuits/ising_coupling.py
quple/circuits/variational_circuits/real_amplitudes.py
quple/classifiers/__init__.py
quple/classifiers/qsvm.py
quple/classifiers/qsvm_logger.py
quple/classifiers/qsvm_qiskit.py
quple/classifiers/vqc.py
quple/classifiers/vqc_logger.py
quple/components/__init__.py
quple/components/descriptors.py
quple/components/gate_ops.py
quple/components/interaction_graphs.py
quple/data_encoding/__init__.py
quple/data_encoding/encoding_circuit.py
quple/data_encoding/encoding_maps.py
quple/data_encoding/first_order_pauli_z_encoding.py
quple/data_encoding/general_pauli_encoding.py
quple/data_encoding/general_pauli_z_encoding.py
quple/data_encoding/second_order_pauli_z_encoding.py
quple/interface/__init__.py
quple/interface/cirq_interface.py
quple/interface/interface_ctrl.py
quple/interface/tfq/__init__.py
quple/interface/tfq/resolvers.py
quple/interface/tfq/tf_resolvers.py
quple/interface/tfq/tf_utils.py
quple/interface/tfq/layers/__init__.py
quple/interface/tfq/layers/pqc.py
quple/interface/tfq/layers/qconv2d.py
quple/interface/tfq/metrics/__init__.py
quple/interface/tfq/metrics/metrics.py
quple/models/__init__.py
quple/models/abstract_model.py
quple/models/classification/__init__.py
quple/models/generative/__init__.py
quple/models/generative/qgan.py
quple/models/generative/qwgan.py
quple/qiskit_interface/__init__.py
quple-0.9.2.7.dist-info/LICENSE
quple-0.9.2.7.dist-info/METADATA
quple-0.9.2.7.dist-info/WHEEL
quple-0.9.2.7.dist-info/top_level.txt
quple-0.9.2.7.dist-info/RECORD
