Metadata-Version: 2.1
Name: quple
Version: 0.9.2.7
Summary: A framework for quantum machine learning in high energy physics
Home-page: https://gitlab.cern.ch/clcheng/quple
Author: Alkaid Cheng
Author-email: chi.lung.cheng@cern.ch
License: UNKNOWN
Platform: UNKNOWN
Classifier: Programming Language :: Python :: 3.5
Classifier: Programming Language :: Python :: 3.6
Classifier: Programming Language :: Python :: 3.7
Classifier: License :: OSI Approved :: MIT License
Classifier: Operating System :: OS Independent
Requires-Python: >=3.5
License-File: LICENSE
Requires-Dist: cirq
Requires-Dist: numpy
Requires-Dist: imageio
Requires-Dist: tensorflow-quantum
